odoo10_addon_l10n_it_account_stamp_ddt-10.0.1.0.0.99.dev4-py3.8-nspkg.pth
odoo/addons/l10n_it_account_stamp_ddt/README.rst
odoo/addons/l10n_it_account_stamp_ddt/__init__.py
odoo/addons/l10n_it_account_stamp_ddt/__manifest__.py
odoo/addons/l10n_it_account_stamp_ddt/i18n/l10n_it_account_stamp_ddt.pot
odoo/addons/l10n_it_account_stamp_ddt/models/__init__.py
odoo/addons/l10n_it_account_stamp_ddt/models/stock_picking_package_preparation.py
odoo/addons/l10n_it_account_stamp_ddt/readme/CONTRIBUTORS.rst
odoo/addons/l10n_it_account_stamp_ddt/readme/DESCRIPTION.rst
odoo/addons/l10n_it_account_stamp_ddt/static/description/icon.png
odoo/addons/l10n_it_account_stamp_ddt/static/description/index.html
odoo10_addon_l10n_it_account_stamp_ddt-10.0.1.0.0.99.dev4.dist-info/METADATA
odoo10_addon_l10n_it_account_stamp_ddt-10.0.1.0.0.99.dev4.dist-info/WHEEL
odoo10_addon_l10n_it_account_stamp_ddt-10.0.1.0.0.99.dev4.dist-info/namespace_packages.txt
odoo10_addon_l10n_it_account_stamp_ddt-10.0.1.0.0.99.dev4.dist-info/top_level.txt
odoo10_addon_l10n_it_account_stamp_ddt-10.0.1.0.0.99.dev4.dist-info/RECORD
